[{"_id":"ETH-416988","txnid":"ETH-416988","amount":150,"firstname":"User","email":"noprovided@example.com","phone":"6303407430","items":[{"id":"play-d1e1f1g1","name":"Bumping Cars","price":150,"image":"/bumping%20cars%20single/IMG_8417.jpg","stall":"Action","quantity":1}],"status":"success","createdAt":"2026-02-07T10:37:07.849Z","paymentId":"S260207074JJNH"},{"_id":"ETH-257553","txnid":"ETH-257553","amount":0,"firstname":"User","email":"noprovided@example.com","phone":"6303407430","items":[{"id":"play-d2e2f2g2","name":"Trampoline Zone","price":0,"image":"/trampoline/trampoline.webp","stall":"Action","quantity":1}],"status":"pending","createdAt":"2026-02-07T10:41:53.813Z"},{"_id":"ETH-517772","txnid":"ETH-517772","amount":0,"firstname":"User","email":"noprovided@example.com","phone":"6303407430","items":[{"id":"play-d2e2f2g2","name":"Trampoline Zone","price":0,"image":"/trampoline/trampoline.webp","stall":"Action","quantity":1}],"status":"pending","createdAt":"2026-02-07T10:41:56.840Z"},{"_id":"ETH-787340","txnid":"ETH-787340","amount":0,"firstname":"User","email":"noprovided@example.com","phone":"6303407430","items":[{"id":"play-d2e2f2g2","name":"Trampoline Zone","price":0,"image":"/trampoline/trampoline.webp","stall":"Action","quantity":2}],"status":"pending","createdAt":"2026-02-07T10:43:52.283Z"},{"_id":"ETH-751998","txnid":"ETH-751998","amount":120,"firstname":"User","email":"noprovided@example.com","phone":"6303407430","items":[{"id":"play-d3e3f3g3","name":"360 Cycle","price":120,"image":"/360%20cycle/360-degree-cycle-500x500.webp","stall":"Rides","quantity":1}],"status":"pending","createdAt":"2026-02-07T10:44:01.750Z"},{"_id":"ETH-168717","txnid":"ETH-168717","amount":120,"firstname":"User","email":"noprovided@example.com","phone":"6303407430","items":[{"id":"play-d3e3f3g3","name":"360 Cycle","price":120,"image":"/360%20cycle/360-degree-cycle-500x500.webp","stall":"Rides","quantity":1},{"id":"play-d2e2f2g2","name":"Trampoline Zone","price":0,"image":"/trampoline/trampoline.webp","stall":"Action","quantity":1}],"status":"success","createdAt":"2026-02-07T10:44:11.154Z","paymentId":"S260207074JJNV"},{"_id":"ETH-166353","txnid":"ETH-166353","amount":100,"firstname":"User","email":"noprovided@example.com","phone":"6303407430","items":[{"id":"play-d8e8f8g8","name":"Train Ride","price":100,"image":"/train%20ticket/IMG_8410.jpg","stall":"Rides","quantity":1}],"status":"success","createdAt":"2026-02-07T10:45:26.038Z","paymentId":"S260207074JJNX"},{"_id":"ETH-104422","txnid":"ETH-104422","amount":350,"firstname":"User","email":"noprovided@example.com","phone":"6303407430","items":[{"id":"play-d6e6f6g6","name":"Free Fall","price":200,"image":"/free%20fall/IMG_8381.jpg","stall":"Adventure","quantity":1},{"id":"play-d7e7f7g7","name":"Sun & Moon","price":150,"image":"/sun%20&%20moon/IMG_8389.jpg","stall":"Rides","quantity":1}],"status":"userCancelled","createdAt":"2026-02-07T10:46:07.348Z"},{"_id":"ETH-405956","txnid":"ETH-405956","amount":350,"firstname":"User","email":"noprovided@example.com","phone":"6303407430","items":[{"id":"play-d6e6f6g6","name":"Free Fall","price":200,"image":"/free%20fall/IMG_8381.jpg","stall":"Adventure","quantity":1},{"id":"play-d7e7f7g7","name":"Sun & Moon","price":150,"image":"/sun%20&%20moon/IMG_8389.jpg","stall":"Rides","quantity":1}],"status":"success","createdAt":"2026-02-07T10:46:16.771Z","paymentId":"S260207074JJNZ"},{"_id":"ETH-962682","txnid":"ETH-962682","amount":150,"firstname":"User","email":"noprovided@example.com","phone":"7780447363","items":[{"id":"play-d1e1f1g1","name":"Bumping Cars","price":150,"image":"/bumping%20cars%20single/IMG_8417.jpg","stall":"Action","quantity":1}],"status":"success","createdAt":"2026-02-07T14:05:11.161Z","paymentId":"S260207074JJU6"},{"_id":"ETH-134405","txnid":"ETH-134405","amount":150,"firstname":"User","email":"noprovided@example.com","phone":"7780447363","items":[{"id":"play-d7e7f7g7","name":"Sun & Moon","price":150,"image":"/sun%20&%20moon/IMG_8389.jpg","stall":"Rides","quantity":1}],"status":"pending","createdAt":"2026-02-07T14:43:33.035Z"},{"_id":"ETH-737891","txnid":"ETH-737891","amount":270,"firstname":"User","email":"noprovided@example.com","phone":"6303407430","items":[{"id":"play-d3e3f3g3","name":"360 Cycle","price":120,"image":"/360%20cycle/360-degree-cycle-500x500.webp","stall":"Rides","quantity":1},{"id":"play-d2e2f2g2","name":"Trampoline Zone","price":150,"image":"/trampoline/trampoline.webp","stall":"Action","quantity":1}],"status":"success","createdAt":"2026-02-08T04:59:35.794Z","paymentId":"S260208074JK0S"},{"_id":"ETH-186139","txnid":"ETH-186139","amount":2000,"firstname":"User","email":"guest@example.com","phone":"6303407433","items":[{"id":"event-1-1770535084913","name":"VIP Dining Suite Booking","price":2000,"quantity":1,"image":"https://images.unsplash.com/photo-1517248135467-4c7edcad34c4?auto=format&fit=crop&w=600&q=80","stall":"Events","details":{"date":"2026-03-23","startTime":"14:30","endTime":"16:30"}}],"status":"pending","createdAt":"2026-02-08T07:18:04.926Z"},{"_id":"ETH-424453","txnid":"ETH-424453","amount":150,"firstname":"User","email":"noprovided@example.com","phone":"6303407433","items":[{"id":"play-d4e4f4g4","name":"Columbus Mini","price":150,"image":"/columbus%20mini/IMG_8407.jpg","stall":"Rides","quantity":1}],"status":"success","createdAt":"2026-02-08T07:19:16.076Z","paymentId":"S260208074JK1L"},{"_id":"ETH-711353","txnid":"ETH-711353","amount":120,"firstname":"User","email":"noprovided@example.com","phone":"6303407430","items":[{"id":"play-d3e3f3g3","name":"360 Cycle","price":120,"image":"/360%20cycle/360-degree-cycle-500x500.webp","stall":"Rides","quantity":1}],"status":"userCancelled","createdAt":"2026-02-08T07:52:15.011Z"},{"_id":"ETH-264465","txnid":"ETH-264465","amount":270,"firstname":"User","email":"noprovided@example.com","phone":"6303407430","items":[{"id":"play-d2e2f2g2","name":"Trampoline Zone","price":150,"image":"/trampoline/trampoline.webp","stall":"Action","quantity":1},{"id":"play-d3e3f3g3","name":"360 Cycle","price":120,"image":"/360%20cycle/360-degree-cycle-500x500.webp","stall":"Rides","quantity":1}],"status":"success","createdAt":"2026-02-08T07:54:56.620Z","paymentId":"S260208074JK1T"},{"_id":"ETH-483735","txnid":"ETH-483735","amount":120,"firstname":"User","email":"noprovided@example.com","phone":"6303407430","items":[{"id":"play-d3e3f3g3","name":"360 Cycle","price":120,"image":"/360%20cycle/360-degree-cycle-500x500.webp","stall":"Rides","quantity":1}],"status":"success","createdAt":"2026-02-08T07:58:59.020Z","paymentId":"S260208074JK1W"},{"_id":"ETH-421038","txnid":"ETH-421038","amount":1000,"firstname":"User","email":"guest@example.com","phone":"6303407430","items":[{"id":"event-1-1770618896844","name":"Celebration Zone Booking","price":1000,"quantity":1,"image":"https://images.unsplash.com/photo-1519167758481-83f550bb49b3?auto=format&fit=crop&w=800&q=80","stall":"Events","details":{"date":"2026-03-02","startTime":"14:30","endTime":"15:30","guests":"65","hours":1}}],"status":"pending","createdAt":"2026-02-09T06:34:56.847Z"},{"_id":"ETH-892907","txnid":"ETH-892907","amount":1000,"firstname":"User","email":"guest@example.com","phone":"6303407430","items":[{"id":"event-1-1770618905268","name":"Celebration Zone Booking","price":1000,"quantity":1,"image":"https://images.unsplash.com/photo-1519167758481-83f550bb49b3?auto=format&fit=crop&w=800&q=80","stall":"Events","details":{"date":"2026-03-02","startTime":"14:30","endTime":"15:30","guests":"65","hours":1}}],"status":"pending","createdAt":"2026-02-09T06:35:05.270Z"},{"_id":"ETH-306680","txnid":"ETH-306680","amount":1000,"firstname":"User","email":"guest@example.com","phone":"6303407430","items":[{"id":"event-1-1770619768049","name":"Celebration Zone Booking","price":1000,"quantity":1,"image":"https://images.unsplash.com/photo-1519167758481-83f550bb49b3?auto=format&fit=crop&w=800&q=80","stall":"Events","details":{"date":"2026-03-02","startTime":"14:30","endTime":"15:30","guests":"65","hours":1}}],"status":"pending","createdAt":"2026-02-09T06:49:28.078Z"},{"_id":"ETH-285014","txnid":"ETH-285014","amount":1000,"firstname":"User","email":"guest@example.com","phone":"6303407430","items":[{"id":"event-1-1770620003568","name":"Celebration Zone Booking","price":1000,"quantity":1,"image":"https://images.unsplash.com/photo-1519167758481-83f550bb49b3?auto=format&fit=crop&w=800&q=80","stall":"Events","details":{"date":"2026-02-20","startTime":"14:30","endTime":"15:30","guests":"52","hours":1}}],"status":"success","createdAt":"2026-02-09T06:53:23.571Z","paymentId":"S260209074JKVM"},{"_id":"ETH-277502","txnid":"ETH-277502","amount":1000,"firstname":"User","email":"guest@example.com","phone":"6303407430","items":[{"id":"event-1-1770620588573","name":"Celebration Zone Booking","price":1000,"quantity":1,"image":"https://images.unsplash.com/photo-1519167758481-83f550bb49b3?auto=format&fit=crop&w=800&q=80","stall":"Events","details":{"date":"2026-02-12","startTime":"14:30","endTime":"15:30","guests":"50","hours":1}}],"status":"success","createdAt":"2026-02-09T07:03:08.574Z","paymentId":"S260209074JKX6"},{"_id":"ETH-431663","txnid":"ETH-431663","amount":1000,"firstname":"munna","email":"guest@example.com","phone":"6303407430","items":[{"id":"event-1-1770627823306","name":"Celebration Zone Booking","price":1000,"quantity":1,"image":"/event%20place.webp","stall":"Events","details":{"date":"2026-02-12","startTime":"15:30","endTime":"16:30","guests":"23","hours":1}}],"status":"success","createdAt":"2026-02-09T09:03:43.310Z","paymentId":"S260209074JLAK"},{"_id":"ETH-876113","txnid":"ETH-876113","amount":500,"firstname":"User","email":"noprovided@example.com","phone":"6303407430","items":[{"id":"play-combo-1","name":"Mega Combo Pack","price":500,"image":"/blur-background-vibrant-ferris-wheel-600nw-2588560711.webp","stall":"play","quantity":1}],"status":"success","createdAt":"2026-02-09T09:19:23.937Z","paymentId":"S260209074JLCR"},{"_id":"ETH-444618","txnid":"ETH-444618","amount":1000,"firstname":"jay","email":"guest@example.com","phone":"6303407430","items":[{"id":"event-1-1770629668643","name":"Celebration Zone Booking","price":1000,"quantity":1,"image":"/event%20place.webp","stall":"Events","details":{"date":"2026-02-12","startTime":"18:30","endTime":"19:30","guests":"25","hours":1}}],"status":"dropped","createdAt":"2026-02-09T09:34:28.647Z"},{"_id":"ETH-498025","txnid":"ETH-498025","amount":1000,"firstname":"jay","email":"guest@example.com","phone":"6303407430","items":[{"id":"event-1-1770629748522","name":"Celebration Zone Booking","price":1000,"quantity":1,"image":"/event%20place.webp","stall":"Events","details":{"date":"2026-02-12","startTime":"18:30","endTime":"19:30","guests":"25","hours":1}}],"status":"success","createdAt":"2026-02-09T09:35:48.523Z","paymentId":"S260209074JLFF"},{"_id":"ETH-526651","txnid":"ETH-526651","amount":1000,"firstname":"jk","email":"guest@example.com","phone":"6303407430","items":[{"id":"event-1-1770631387052","name":"Celebration Zone Booking","price":1000,"quantity":1,"image":"/event%20place.webp","stall":"Events","details":{"date":"2026-02-11","startTime":"14:02","endTime":"15:02","guests":"20","hours":1}}],"status":"success","createdAt":"2026-02-09T10:03:07.054Z","paymentId":"S260209074JLJB"},{"_id":"ETH-660318","txnid":"ETH-660318","amount":150,"firstname":"User","email":"noprovided@example.com","phone":"6303407430","items":[{"id":"play-d1e1f1g1","name":"Bumping Cars","price":150,"image":"/bumping%20cars%20single/IMG_8417.jpg","stall":"Action","quantity":1}],"status":"userCancelled","createdAt":"2026-02-09T10:13:05.749Z"}]
